pyCalor/__init__.py
pyCalor/examples.py
pyCalor/hf.json
pyCalor/plots.py
pyCalor/thermo.py
pyCalor/units.py
pyCalor/utils.py
pycalor-1.0.21.dist-info/licenses/LICENSE
pycalor-1.0.21.dist-info/METADATA
pycalor-1.0.21.dist-info/WHEEL
pycalor-1.0.21.dist-info/top_level.txt
pycalor-1.0.21.dist-info/RECORD
