Metadata-Version: 2.4
Name: pyCalor
Version: 1.0.21
Summary: A Python module for performing thermodynamic calculations used in teaching ME40 at the University of California, Berkeley.
Author-email: Michael Frenklach <frenklach@berkeley.edu>, Thomas Schutzius <tschutzius@berkeley.edu>
License-Expression: GPL-3.0-or-later
Project-URL: Homepage, https://github.berkeley.edu/tschutzius/me40
Keywords: thermodynamics,chemistry,physics
Classifier: Programming Language :: Python :: 3
Classifier: Operating System :: OS Independent
Requires-Python: >=3.8
License-File: LICENSE
Requires-Dist: CoolProp
Requires-Dist: igraph
Dynamic: license-file
